{
  "id": "image_beside_text",
  "type": "SharedSlice",
  "name": "ImageBesideText",
  "description": "ImageBesideText",
  "variations": [
    {
      "id": "imageLeft",
      "name": "ImageLeft",
      "docURL": "...",
      "version": "initial",
      "description": "Default",
      "imageUrl": "",
      "primary": {
        "image": {
          "type": "Image",
          "config": {
            "label": "Image",
            "constraint": {},
            "thumbnails": []
          }
        },
        "title": {
          "type": "StructuredText",
          "config": {
            "label": "Title",
            "placeholder": "",
            "allowTargetBlank": true,
            "single": "heading1,heading2,heading3,heading4,heading5,heading6,strong,em"
          }
        },
        "subtitle": {
          "type": "Text",
          "config": {
            "label": "Subtitle",
            "placeholder": ""
          }
        },
        "description": {
          "type": "StructuredText",
          "config": {
            "label": "Description",
            "placeholder": "",
            "allowTargetBlank": true,
            "multi": "paragraph,preformatted,heading3,heading4,heading5,heading6,strong,em,hyperlink,image,embed,list-item,o-list-item,rtl"
          }
        },
        "link": {
          "type": "Link",
          "config": {
            "label": "Link",
            "placeholder": "",
            "select": null,
            "allowTargetBlank": true,
            "allowText": true,
            "repeat": false
          }
        }
      },
      "items": {}
    },
    {
      "id": "imageRight",
      "name": "ImageRight",
      "docURL": "...",
      "version": "initial",
      "description": "Default",
      "imageUrl": "",
      "primary": {
        "image": {
          "type": "Image",
          "config": {
            "label": "Image",
            "constraint": {},
            "thumbnails": []
          }
        },
        "title": {
          "type": "StructuredText",
          "config": {
            "label": "Title",
            "placeholder": "",
            "allowTargetBlank": true,
            "single": "heading1,heading2,heading3,heading4,heading5,heading6,strong,em"
          }
        },
        "subtitle": {
          "type": "Text",
          "config": {
            "label": "Subtitle",
            "placeholder": ""
          }
        },
        "description": {
          "type": "StructuredText",
          "config": {
            "label": "Description",
            "placeholder": "",
            "allowTargetBlank": true,
            "multi": "paragraph,preformatted,heading3,heading4,heading5,heading6,strong,em,hyperlink,image,embed,list-item,o-list-item,rtl"
          }
        },
        "link": {
          "type": "Link",
          "config": {
            "label": "Link",
            "placeholder": "",
            "select": null,
            "allowTargetBlank": true,
            "allowText": true,
            "repeat": false
          }
        }
      },
      "items": {}
    }
  ]
}
